{"pageProps":{"product":{"id":3,"name":"Mobile","desc":"A customer mobile application development that let you connect with your customer to track his buy behaviors and give you a insightful dashboard to measure your conversion rate, not only that but it give you a instant notification sender that let you connect with you customer instantly ","photo":"mobile.jpg","longDesc":"A customer mobile application development that let you connect with your customer to track his buy behaviors and give you a insightful dashboard to measure your conversion rate, not only that but it give you a instant notification sender that let you connect with you customer instantly ","images":[{"id":1,"url":"m1.jpg"},{"id":2,"url":"m2.jpeg"},{"id":3,"url":"m3.jpeg"},{"id":4,"url":"m4.png"},{"id":5,"url":"m5.png"},{"id":6,"url":"m6.png"}]}},"__N_SSG":true}